pycomment/__init__.py
pycomment/__main__.py
pycomment/__version__.py
pycomment/_fixer_util.py
pycomment/capture.py
pycomment/emit.py
pycomment/langhelpers.py
pycomment/parse.py
pycomment/transform.py
pycomment/tests/__init__.py
pycomment/tests/_fakearray.py
pycomment/tests/test_capture.py
pycomment/tests/test_emit.py
pycomment/tests/testing.py
pycomment-0.2.0.dist-info/METADATA
pycomment-0.2.0.dist-info/WHEEL
pycomment-0.2.0.dist-info/entry_points.txt
pycomment-0.2.0.dist-info/RECORD
