Metadata-Version: 2.4
Name: pycomment
Version: 0.2.0
Summary: with repr value as comment
Project-URL: Homepage, https://github.com/podhmo/pycomment
Project-URL: Repository, https://github.com/podhmo/pycomment
Author-email: podhmo <ababjam61+github@gmail.com>
Classifier: Programming Language :: Python
Classifier: Programming Language :: Python :: 3
Classifier: Programming Language :: Python :: 3.10
Classifier: Programming Language :: Python :: 3.11
Classifier: Programming Language :: Python :: 3.12
Classifier: Programming Language :: Python :: 3.13
Classifier: Programming Language :: Python :: Implementation :: CPython
Requires-Python: >=3.10
Requires-Dist: black
